LICENSE
MANIFEST.in
README.md
listen.py
setup.cfg
setup.py
versioneer.py
telefilebot/__init__.py
telefilebot/_version.py
telefilebot/bot.py
telefilebot/directory.py
telefilebot.egg-info/PKG-INFO
telefilebot.egg-info/SOURCES.txt
telefilebot.egg-info/dependency_links.txt
telefilebot.egg-info/entry_points.txt
telefilebot.egg-info/requires.txt
telefilebot.egg-info/top_level.txt
telefilebot/data/__init__.py
telefilebot/io/__init__.py
telefilebot/utils/__init__.py
telefilebot/utils/logging.py
telefilebot/utils/read_input_file.py